lab5-pipe1/nerv_2stage.sv
/*
 *  NERV -- Naive Educational RISC-V Processor
 *
 *  Copyright (C) 2020  Claire Xenia Wolf <claire@yosyshq.com>
 *
 *  Permission to use, copy, modify, and/or distribute this software for any
 *  purpose with or without fee is hereby granted, provided that the above
 *  copyright notice and this permission notice appear in all copies.
 *
 *  THE SOFTWARE IS PROVIDED "AS IS" AND THE AUTHOR DISCLAIMS ALL WARRANTIES
 *  WITH REGARD TO THIS SOFTWARE INCLUDING ALL IMPLIED WARRANTIES OF
 *  MERCHANTABILITY AND FITNESS. IN NO EVENT SHALL THE AUTHOR BE LIABLE FOR
 *  ANY SPECIAL, DIRECT, INDIRECT, OR CONSEQUENTIAL DAMAGES OR ANY DAMAGES
 *  WHATSOEVER RESULTING FROM LOSS OF USE, DATA OR PROFITS, WHETHER IN AN
 *  ACTION OF CONTRACT, NEGLIGENCE OR OTHER TORTIOUS ACTION, ARISING OUT OF
 *  OR IN CONNECTION WITH THE USE OR PERFORMANCE OF THIS SOFTWARE.
 *
 */

module nerv_2stage #(
	parameter [31:0] RESET_ADDR = 32'h 0000_0000,
	parameter integer NUMREGS = 32
) (
	input clock,
	input reset,
	output trap,

	// we have 2 external memories
	// one is instruction memory
	output [31:0] imem_addr,
	input  [31:0] imem_data,

	// the other is data memory
	output        dmem_valid,
	output [31:0] dmem_addr,
	output [ 3:0] dmem_wstrb,
	output [31:0] dmem_wdata,
	input  [31:0] dmem_rdata
);
	logic mem_wr_enable;
	logic [31:0] mem_wr_addr;
	logic [31:0] mem_wr_data;
	logic [3:0] mem_wr_strb;

	logic mem_rd_enable;
	logic [31:0] mem_rd_addr;
	logic [4:0] mem_rd_reg;
	logic [4:0] mem_rd_func;

	logic mem_rd_enable_q;
	logic [4:0] mem_rd_reg_q;
	logic [4:0] mem_rd_func_q;

	// delayed copies of mem_rd
	always @(posedge clock) begin
		mem_rd_enable_q <= mem_rd_enable;
		mem_rd_reg_q <= mem_rd_reg;
		mem_rd_func_q <= mem_rd_func;
		if (reset) begin
			mem_rd_enable_q <= 0;
		end
	end

	// memory signals
	assign dmem_valid = mem_wr_enable || mem_rd_enable;
	assign dmem_addr  = mem_wr_enable ? mem_wr_addr : mem_rd_enable ? mem_rd_addr : 32'h x;
	assign dmem_wstrb = mem_wr_enable ? mem_wr_strb : mem_rd_enable ? 4'h 0 : 4'h x;
	assign dmem_wdata = mem_wr_enable ? mem_wr_data : 32'h x;

	// registers, instruction reg, program counter, next pc
	logic [31:0] regfile [0:NUMREGS-1];
	wire [31:0] insn;
	logic [31:0] npc;
	logic [31:0] pc;

	logic [31:0] imem_addr_q;

	always @(posedge clock) begin
		imem_addr_q <= imem_addr;
	end

	// instruction memory pointer
	assign imem_addr = (trap || mem_rd_enable_q || (!stage_1_en) ) ? imem_addr_q : npc;
	assign insn = imem_data;

	// rs1 and rs2 are source for the instruction
	wire [31:0] rs1_value = !insn_rs1 ? 0 : regfile[insn_rs1];
	wire [31:0] rs2_value = !insn_rs2 ? 0 : regfile[insn_rs2];

	// components of the instruction
	wire [6:0] insn_funct7;
	wire [4:0] insn_rs2;
	wire [4:0] insn_rs1;
	wire [2:0] insn_funct3;
	wire [4:0] insn_rd;
	wire [6:0] insn_opcode;

	// split R-type instruction - see section 2.2 of RiscV spec
	assign {insn_funct7, insn_rs2, insn_rs1, insn_funct3, insn_rd, insn_opcode} = insn;

	// setup for I, S, B & J type instructions
	// I - short immediates and loads
	wire [11:0] imm_i;
	assign imm_i = insn[31:20];

	// S - stores
	wire [11:0] imm_s;
	assign imm_s[11:5] = insn_funct7, imm_s[4:0] = insn_rd;

	// B - conditionals
	wire [12:0] imm_b;
	assign {imm_b[12], imm_b[10:5]} = insn_funct7, {imm_b[4:1], imm_b[11]} = insn_rd, imm_b[0] = 1'b0;

	// J - unconditional jumps
	wire [20:0] imm_j;
	assign {imm_j[20], imm_j[10:1], imm_j[11], imm_j[19:12], imm_j[0]} = {insn[31:12], 1'b0};

	wire [31:0] imm_i_sext = $signed(imm_i);
	wire [31:0] imm_s_sext = $signed(imm_s);
	wire [31:0] imm_b_sext = $signed(imm_b);
	wire [31:0] imm_j_sext = $signed(imm_j);

	// opcodes - see section 19 of RiscV spec
	localparam OPCODE_LOAD       = 7'b 00_000_11;
	localparam OPCODE_STORE      = 7'b 01_000_11;
	localparam OPCODE_MADD       = 7'b 10_000_11;
	localparam OPCODE_BRANCH     = 7'b 11_000_11;

	localparam OPCODE_LOAD_FP    = 7'b 00_001_11;
	localparam OPCODE_STORE_FP   = 7'b 01_001_11;
	localparam OPCODE_MSUB       = 7'b 10_001_11;
	localparam OPCODE_JALR       = 7'b 11_001_11;

	localparam OPCODE_CUSTOM_0   = 7'b 00_010_11;
	localparam OPCODE_CUSTOM_1   = 7'b 01_010_11;
	localparam OPCODE_NMSUB      = 7'b 10_010_11;
	localparam OPCODE_RESERVED_0 = 7'b 11_010_11;

	localparam OPCODE_MISC_MEM   = 7'b 00_011_11;
	localparam OPCODE_AMO        = 7'b 01_011_11;
	localparam OPCODE_NMADD      = 7'b 10_011_11;
	localparam OPCODE_JAL        = 7'b 11_011_11;

	localparam OPCODE_OP_IMM     = 7'b 00_100_11;
	localparam OPCODE_OP         = 7'b 01_100_11;
	localparam OPCODE_OP_FP      = 7'b 10_100_11;
	localparam OPCODE_SYSTEM     = 7'b 11_100_11;

	localparam OPCODE_AUIPC      = 7'b 00_101_11;
	localparam OPCODE_LUI        = 7'b 01_101_11;
	localparam OPCODE_RESERVED_1 = 7'b 10_101_11;
	localparam OPCODE_RESERVED_2 = 7'b 11_101_11;

	localparam OPCODE_OP_IMM_32  = 7'b 00_110_11;
	localparam OPCODE_OP_32      = 7'b 01_110_11;
	localparam OPCODE_CUSTOM_2   = 7'b 10_110_11;
	localparam OPCODE_CUSTOM_3   = 7'b 11_110_11;

	// next write, next destination (rd), illegal instruction registers
	logic next_wr;
	logic [31:0] next_rd;
	logic illinsn;

	logic trapped;
	logic trapped_q;
	assign trap = trapped;



	// 2 stage pipeline controls. stage 1 = fetch and increment counter. stage 2, execute, memory, write back.
	logic stage_1_en;    // turn on and off.
	logic stage_1_en_q;  //
	logic stage_1_ready; // waiting for data to be taken.


	always_comb begin


		// pipelining.
		stage_1_en = stage_1_en_q;

		// these codes disrupt the pipeline by causing the next instruction to be an unknown distance ahead.
		if (  
			insn_opcode == OPCODE_JAL
		||  insn_opcode == OPCODE_JALR
		||  insn_opcode == OPCODE_BRANCH
		||  insn_opcode == OPCODE_AUIPC
		 ) 
		begin
			stage_1_en = 0;
		end
		else begin
			stage_1_en = 1;
		end


		// advance pc
		npc = pc + 4;

		// defaults for read, write
		next_wr = 0;
		next_rd = 0;
		illinsn = 0;

		mem_wr_enable = 0;
		mem_wr_addr = 'hx;
		mem_wr_data = 'hx;
		mem_wr_strb = 'hx;

		mem_rd_enable = 0;
		mem_rd_addr = 'hx;
		mem_rd_reg = 'hx;
		mem_rd_func = 'hx;

		// act on opcodes
		case (insn_opcode)
			// Load Upper Immediate
			OPCODE_LUI: begin
				next_wr = 1;
				next_rd = insn[31:12] << 12;
			end
			// Add Upper Immediate to Program Counter
			OPCODE_AUIPC: begin
				next_wr = 1;
				next_rd = (insn[31:12] << 12) + pc;
			end
			// Jump And Link (unconditional jump)
			OPCODE_JAL: begin
				next_wr = 1;
				next_rd = npc;
				npc = pc + imm_j_sext;
				if (npc & 32'b 11) begin
					illinsn = 1;
					npc = npc & ~32'b 11;
				end
			end
			// Jump And Link Register (indirect jump)
			OPCODE_JALR: begin
				case (insn_funct3)
					3'b 000 /* JALR */: begin
						next_wr = 1;
						next_rd = npc;
						npc = (rs1_value + imm_i_sext) & ~32'b 1;
					end
					default: illinsn = 1;
				endcase
				if (npc & 32'b 11) begin
					illinsn = 1;
					npc = npc & ~32'b 11;
				end
			end
			// branch instructions: Branch If Equal, Branch Not Equal, Branch Less Than, Branch Greater Than, Branch Less Than Unsigned, Branch Greater Than Unsigned
			OPCODE_BRANCH: begin
				case (insn_funct3)
					3'b 000 /* BEQ  */: begin if (rs1_value == rs2_value) npc = pc + imm_b_sext; end
					3'b 001 /* BNE  */: begin if (rs1_value != rs2_value) npc = pc + imm_b_sext; end
					3'b 100 /* BLT  */: begin if ($signed(rs1_value) < $signed(rs2_value)) npc = pc + imm_b_sext; end
					3'b 101 /* BGE  */: begin if ($signed(rs1_value) >= $signed(rs2_value)) npc = pc + imm_b_sext; end
					3'b 110 /* BLTU */: begin if (rs1_value < rs2_value) npc = pc + imm_b_sext; end
					3'b 111 /* BGEU */: begin if (rs1_value >= rs2_value) npc = pc + imm_b_sext; end
					default: illinsn = 1;
				endcase
				if (npc & 32'b 11) begin
					illinsn = 1;
					npc = npc & ~32'b 11;
				end
			end
			// load from memory into rd: Load Byte, Load Halfword, Load Word, Load Byte Unsigned, Load Halfword Unsigned
			OPCODE_LOAD: begin
				mem_rd_addr = rs1_value + imm_i_sext;
				casez ({insn_funct3, mem_rd_addr[1:0]})
					5'b 000_zz /* LB  */,
					5'b 001_z0 /* LH  */,
					5'b 010_00 /* LW  */,
					5'b 100_zz /* LBU */,
					5'b 101_z0 /* LHU */: begin
						mem_rd_enable = 1;
						mem_rd_reg = insn_rd;
						mem_rd_func = {mem_rd_addr[1:0], insn_funct3};
						mem_rd_addr = {mem_rd_addr[31:2], 2'b 00};
					end
					default: illinsn = 1;
				endcase
			end
			// store to memory instructions: Store Byte, Store Halfword, Store Word
			OPCODE_STORE: begin
				mem_wr_addr = rs1_value + imm_s_sext;
				casez ({insn_funct3, mem_wr_addr[1:0]})
					5'b 000_zz /* SB */,
					5'b 001_z0 /* SH */,
					5'b 010_00 /* SW */: begin
						mem_wr_enable = 1;
						mem_wr_data = rs2_value;
						mem_wr_strb = 4'b 1111;
						case (insn_funct3)
							3'b 000 /* SB  */: begin mem_wr_strb = 4'b 0001; end
							3'b 001 /* SH  */: begin mem_wr_strb = 4'b 0011; end
							3'b 010 /* SW  */: begin mem_wr_strb = 4'b 1111; end
						endcase
						mem_wr_data = mem_wr_data << (8*mem_wr_addr[1:0]);
						mem_wr_strb = mem_wr_strb << mem_wr_addr[1:0];
						mem_wr_addr = {mem_wr_addr[31:2], 2'b 00};
					end
					default: illinsn = 1;
				endcase
			end
			// immediate ALU instructions: Add Immediate, Set Less Than Immediate, Set Less Than Immediate Unsigned, XOR Immediate,
			// OR Immediate, And Immediate, Shift Left Logical Immediate, Shift Right Logical Immediate, Shift Right Arithmetic Immediate
			OPCODE_OP_IMM: begin
				casez ({insn_funct7, insn_funct3})
					10'b zzzzzzz_000 /* ADDI  */: begin next_wr = 1; next_rd = rs1_value + imm_i_sext; end
					10'b zzzzzzz_010 /* SLTI  */: begin next_wr = 1; next_rd = $signed(rs1_value) < $signed(imm_i_sext); end
					10'b zzzzzzz_011 /* SLTIU */: begin next_wr = 1; next_rd = rs1_value < imm_i_sext; end
					10'b zzzzzzz_100 /* XORI  */: begin next_wr = 1; next_rd = rs1_value ^ imm_i_sext; end
					10'b zzzzzzz_110 /* ORI   */: begin next_wr = 1; next_rd = rs1_value | imm_i_sext; end
					10'b zzzzzzz_111 /* ANDI  */: begin next_wr = 1; next_rd = rs1_value & imm_i_sext; end
					10'b 0000000_001 /* SLLI  */: begin next_wr = 1; next_rd = rs1_value << insn[24:20]; end
					10'b 0000000_101 /* SRLI  */: begin next_wr = 1; next_rd = rs1_value >> insn[24:20]; end
					10'b 0100000_101 /* SRAI  */: begin next_wr = 1; next_rd = $signed(rs1_value) >>> insn[24:20]; end
					default: illinsn = 1;
				endcase
			end
			OPCODE_OP: begin
			// ALU instructions: Add, Subtract, Shift Left Logical, Set Left Than, Set Less Than Unsigned, XOR, Shift Right Logical,
			// Shift Right Arithmetic, OR, AND
				case ({insn_funct7, insn_funct3})
					10'b 0000000_000 /* ADD  */: begin next_wr = 1; next_rd = rs1_value + rs2_value; end
					10'b 0100000_000 /* SUB  */: begin next_wr = 1; next_rd = rs1_value - rs2_value; end
					10'b 0000000_001 /* SLL  */: begin next_wr = 1; next_rd = rs1_value << rs2_value[4:0]; end
					10'b 0000000_010 /* SLT  */: begin next_wr = 1; next_rd = $signed(rs1_value) < $signed(rs2_value); end
					10'b 0000000_011 /* SLTU */: begin next_wr = 1; next_rd = rs1_value < rs2_value; end
					10'b 0000000_100 /* XOR  */: begin next_wr = 1; next_rd = rs1_value ^ rs2_value; end
					10'b 0000000_101 /* SRL  */: begin next_wr = 1; next_rd = rs1_value >> rs2_value[4:0]; end
					10'b 0100000_101 /* SRA  */: begin next_wr = 1; next_rd = $signed(rs1_value) >>> rs2_value[4:0]; end
					10'b 0000000_110 /* OR   */: begin next_wr = 1; next_rd = rs1_value | rs2_value; end
					10'b 0000000_111 /* AND  */: begin next_wr = 1; next_rd = rs1_value & rs2_value; end
					default: illinsn = 1;
				endcase
			end
			default: illinsn = 1;
		endcase

		// if last cycle was a memory read, then this cycle is the 2nd part of it and imem_data will not be a valid instruction
		if (mem_rd_enable_q) begin
			npc = pc;
			next_wr = 0;
			illinsn = 0;
			mem_rd_enable = 0;
			mem_wr_enable = 0;
		end

		// reset
		if (reset || reset_q) begin
			npc = RESET_ADDR;
			next_wr = 0;
			illinsn = 0;
			mem_rd_enable = 0;
			mem_wr_enable = 0;
		end
	end

	logic reset_q;
	logic [31:0] mem_rdata;

	// mem read functions: Lower and Upper Bytes, signed and unsigned
	always_comb begin
		mem_rdata = dmem_rdata >> (8*mem_rd_func_q[4:3]);
		case (mem_rd_func_q[2:0])
			3'b 000 /* LB  */: begin mem_rdata = $signed(mem_rdata[7:0]); end
			3'b 001 /* LH  */: begin mem_rdata = $signed(mem_rdata[15:0]); end
			3'b 100 /* LBU */: begin mem_rdata = mem_rdata[7:0]; end
			3'b 101 /* LHU */: begin mem_rdata = mem_rdata[15:0]; end
		endcase
	end

	// every cycle
	always @(posedge clock) begin
		reset_q <= reset;
		trapped_q <= trapped;
		stage_1_en_q <= stage_1_en;

		// increment pc if possible
		if (!trapped && !reset && !reset_q) begin
			if (illinsn)
				trapped <= 1;
			pc <= npc;
			// update registers from memory or rd (destination)
			if (mem_rd_enable_q || next_wr)
				regfile[mem_rd_enable_q ? mem_rd_reg_q : insn_rd] <= mem_rd_enable_q ? mem_rdata : next_rd;
		end
        if (trapped)
            $display("regfile[10]=%d", regfile[10]);

		// reset
		if (reset || reset_q) begin
			pc <= RESET_ADDR - (reset ? 4 : 0);
			trapped <= 0;
		end
	end

endmodule

lab6-pipe2/testbench.sv
/*
 *  NERV -- Naive Educational RISC-V Processor
 *
 *  Copyright (C) 2020  N. Engelhardt <nak@yosyshq.com>
 *
 *  Permission to use, copy, modify, and/or distribute this software for any
 *  purpose with or without fee is hereby granted, provided that the above
 *  copyright notice and this permission notice appear in all copies.
 *
 *  THE SOFTWARE IS PROVIDED "AS IS" AND THE AUTHOR DISCLAIMS ALL WARRANTIES
 *  WITH REGARD TO THIS SOFTWARE INCLUDING ALL IMPLIED WARRANTIES OF
 *  MERCHANTABILITY AND FITNESS. IN NO EVENT SHALL THE AUTHOR BE LIABLE FOR
 *  ANY SPECIAL, DIRECT, INDIRECT, OR CONSEQUENTIAL DAMAGES OR ANY DAMAGES
 *  WHATSOEVER RESULTING FROM LOSS OF USE, DATA OR PROFITS, WHETHER IN AN
 *  ACTION OF CONTRACT, NEGLIGENCE OR OTHER TORTIOUS ACTION, ARISING OUT OF
 *  OR IN CONNECTION WITH THE USE OR PERFORMANCE OF THIS SOFTWARE.
 *
 */

module testbench(clock, reset);

localparam MEM_ADDR_WIDTH = 16;

input reg clock;
input reg reset;
wire trap;

wire [31:0] imem_addr;
reg  [31:0] imem_data;

wire        dmem_valid;
wire [31:0] dmem_addr;
wire [ 3:0] dmem_wstrb;
wire [31:0] dmem_wdata;
reg  [31:0] dmem_rdata;

reg [7:0] mem [0:(1<<MEM_ADDR_WIDTH)-1];

wire wr_in_mem_range = (dmem_addr[31:2] < (1<<MEM_ADDR_WIDTH));
wire wr_in_output = (dmem_addr == 32'h 02000000);

reg [31:0] out;
reg out_valid;
always @(posedge clock) begin
	if (out_valid) begin
		$write("%c", out[7:0]);
`ifndef VERILATOR
		$fflush();
`endif
	end
end

always @(posedge clock) begin
	if (imem_addr >= (1<<MEM_ADDR_WIDTH)) begin
		$display("Memory access out of range: imem_addr = 0x%08x", imem_addr);
	end
	if (dmem_valid && !(wr_in_mem_range || wr_in_output)) begin
		$display("Memory access out of range: dmem_addr = 0x%08x", dmem_addr);
	end
end

integer i;
always @(posedge clock) begin
	out <= 32'h 0;
	out_valid <= 1'b0;
	imem_data <= {
		mem[{imem_addr[MEM_ADDR_WIDTH-1:2], 2'b11}],
		mem[{imem_addr[MEM_ADDR_WIDTH-1:2], 2'b10}],
		mem[{imem_addr[MEM_ADDR_WIDTH-1:2], 2'b01}],
		mem[{imem_addr[MEM_ADDR_WIDTH-1:2], 2'b00}]
	};
	if (!reset) begin

		if (dmem_valid) begin
			dmem_rdata <= {
				mem[{dmem_addr[MEM_ADDR_WIDTH-1:2], 2'b11}],
				mem[{dmem_addr[MEM_ADDR_WIDTH-1:2], 2'b10}],
				mem[{dmem_addr[MEM_ADDR_WIDTH-1:2], 2'b01}],
				mem[{dmem_addr[MEM_ADDR_WIDTH-1:2], 2'b00}]
			};
			for (i=0;i<4;i=i+1) begin
				if (dmem_wstrb[i]) begin
					if (wr_in_mem_range) begin
						mem[{dmem_addr[MEM_ADDR_WIDTH-1:2], i[1:0]}] <= dmem_wdata[(i*8)+: 8];
					end
					if (wr_in_output) begin
						out[(i*8)+: 8] <= dmem_wdata[(i*8)+: 8];
						out_valid <= 1'b1;
					end
					dmem_rdata <= 'hx;
				end
			end
		end else begin
			dmem_rdata <= 32'h XXXX_XXXX;
		end
	end
end

initial begin
	$readmemh("firmware.hex", mem);
end

nerv_2stage dut (
	.clock(clock),
	.reset(reset),
	.trap(trap),

	.imem_addr(imem_addr),
	.imem_data(imem_data),

	.dmem_valid(dmem_valid),
	.dmem_addr(dmem_addr),
	.dmem_wstrb(dmem_wstrb),
	.dmem_wdata(dmem_wdata),
	.dmem_rdata(dmem_rdata)
);

reg [31:0] cycles = 0;

always @(posedge clock) begin
	cycles <= cycles + 32'h1;
	if (trap) begin
		$display("Simulated %0d cycles", cycles);
		$finish;
	end
end



endmodule

lab5-pipe1/gtkwave.vcd
$version Generated by VerilatedVcd $end
$date Fri Sep 23 13:49:49 2022
 $end
$timescale   1ns $end

 $scope module TOP $end
  $var wire  1 1' clock $end
  $var wire  1 9' reset $end
  $scope module testbench $end
   $var wire 32 A' MEM_ADDR_WIDTH [31:0] $end
   $var wire  1 1' clock $end
   $var wire 32 # cycles [31:0] $end
   $var wire 32 -! dmem_addr [31:0] $end
   $var wire 32 g" dmem_rdata [31:0] $end
   $var wire  1 %! dmem_valid $end
   $var wire 32 =! dmem_wdata [31:0] $end
   $var wire  4 5! dmem_wstrb [3:0] $end
   $var wire 32 !# i [31:0] $end
   $var wire 32 { imem_addr [31:0] $end
   $var wire 32 _" imem_data [31:0] $end
   $var wire 32 o" out [31:0] $end
   $var wire  1 w" out_valid $end
   $var wire  1 9' reset $end
   $var wire  1 W" trap $end
   $var wire  1 E! wr_in_mem_range $end
   $var wire  1 M! wr_in_output $end
   $scope module dut $end
    $var wire 32 Q' NUMREGS [31:0] $end
    $var wire  7 c( OPCODE_AMO [6:0] $end
    $var wire  7 =) OPCODE_AUIPC [6:0] $end
    $var wire  7 q' OPCODE_BRANCH [6:0] $end
    $var wire  7 ;( OPCODE_CUSTOM_0 [6:0] $end
    $var wire  7 C( OPCODE_CUSTOM_1 [6:0] $end
    $var wire  7 m) OPCODE_CUSTOM_2 [6:0] $end
    $var wire  7 u) OPCODE_CUSTOM_3 [6:0] $end
    $var wire  7 s( OPCODE_JAL [6:0] $end
    $var wire  7 3( OPCODE_JALR [6:0] $end
    $var wire  7 Y' OPCODE_LOAD [6:0] $end
    $var wire  7 y' OPCODE_LOAD_FP [6:0] $end
    $var wire  7 E) OPCODE_LUI [6:0] $end
    $var wire  7 i' OPCODE_MADD [6:0] $end
    $var wire  7 [( OPCODE_MISC_MEM [6:0] $end
    $var wire  7 +( OPCODE_MSUB [6:0] $end
    $var wire  7 k( OPCODE_NMADD [6:0] $end
    $var wire  7 K( OPCODE_NMSUB [6:0] $end
    $var wire  7 %) OPCODE_OP [6:0] $end
    $var wire  7 e) OPCODE_OP_32 [6:0] $end
    $var wire  7 -) OPCODE_OP_FP [6:0] $end
    $var wire  7 {( OPCODE_OP_IMM [6:0] $end
    $var wire  7 ]) OPCODE_OP_IMM_32 [6:0] $end
    $var wire  7 S( OPCODE_RESERVED_0 [6:0] $end
    $var wire  7 M) OPCODE_RESERVED_1 [6:0] $end
    $var wire  7 U) OPCODE_RESERVED_2 [6:0] $end
    $var wire  7 a' OPCODE_STORE [6:0] $end
    $var wire  7 #( OPCODE_STORE_FP [6:0] $end
    $var wire  7 5) OPCODE_SYSTEM [6:0] $end
    $var wire 32 I' RESET_ADDR [31:0] $end
    $var wire  1 1' clock $end
    $var wire 32 -! dmem_addr [31:0] $end
    $var wire 32 g" dmem_rdata [31:0] $end
    $var wire  1 %! dmem_valid $end
    $var wire 32 =! dmem_wdata [31:0] $end
    $var wire  4 5! dmem_wstrb [3:0] $end
    $var wire  1 O" illinsn $end
    $var wire 32 { imem_addr [31:0] $end
    $var wire 32 /& imem_addr_q [31:0] $end
    $var wire 32 _" imem_data [31:0] $end
    $var wire 13 C imm_b [12:0] $end
    $var wire 32 [ imm_b_sext [31:0] $end
    $var wire 12 g& imm_i [11:0] $end
    $var wire 32 o& imm_i_sext [31:0] $end
    $var wire 21 K imm_j [20:0] $end
    $var wire 32 c imm_j_sext [31:0] $end
    $var wire 12 ; imm_s [11:0] $end
    $var wire 32 S imm_s_sext [31:0] $end
    $var wire 32 _" insn [31:0] $end
    $var wire  3 O& insn_funct3 [2:0] $end
    $var wire  7 7& insn_funct7 [6:0] $end
    $var wire  7 _& insn_opcode [6:0] $end
    $var wire  5 W& insn_rd [4:0] $end
    $var wire  5 G& insn_rs1 [4:0] $end
    $var wire  5 ?& insn_rs2 [4:0] $end
    $var wire 32 }! mem_rd_addr [31:0] $end
    $var wire  1 u! mem_rd_enable $end
    $var wire  1 )# mem_rd_enable_q $end
    $var wire  5 /" mem_rd_func [4:0] $end
    $var wire  5 9# mem_rd_func_q [4:0] $end
    $var wire  5 '" mem_rd_reg [4:0] $end
    $var wire  5 1# mem_rd_reg_q [4:0] $end
    $var wire 32 s mem_rdata [31:0] $end
    $var wire 32 ]! mem_wr_addr [31:0] $end
    $var wire 32 e! mem_wr_data [31:0] $end
    $var wire  1 U! mem_wr_enable $end
    $var wire  4 m! mem_wr_strb [3:0] $end
    $var wire 32 G" next_rd [31:0] $end
    $var wire  1 ?" next_wr $end
    $var wire 32 7" npc [31:0] $end
    $var wire 32 '& pc [31:0] $end
    $var wire 32 A# regfile(0) [31:0] $end
    $var wire 32 B# regfile(1) [31:0] $end
    $var wire 32 K# regfile(10) [31:0] $end
    $var wire 32 L# regfile(11) [31:0] $end
    $var wire 32 M# regfile(12) [31:0] $end
    $var wire 32 N# regfile(13) [31:0] $end
    $var wire 32 O# regfile(14) [31:0] $end
    $var wire 32 P# regfile(15) [31:0] $end
    $var wire 32 Q# regfile(16) [31:0] $end
    $var wire 32 R# regfile(17) [31:0] $end
    $var wire 32 S# regfile(18) [31:0] $end
    $var wire 32 T# regfile(19) [31:0] $end
    $var wire 32 C# regfile(2) [31:0] $end
    $var wire 32 U# regfile(20) [31:0] $end
    $var wire 32 V# regfile(21) [31:0] $end
    $var wire 32 W# regfile(22) [31:0] $end
    $var wire 32 X# regfile(23) [31:0] $end
    $var wire 32 Y# regfile(24) [31:0] $end
    $var wire 32 Z# regfile(25) [31:0] $end
    $var wire 32 [# regfile(26) [31:0] $end
    $var wire 32 \# regfile(27) [31:0] $end
    $var wire 32 ]# regfile(28) [31:0] $end
    $var wire 32 ^# regfile(29) [31:0] $end
    $var wire 32 D# regfile(3) [31:0] $end
    $var wire 32 _# regfile(30) [31:0] $end
    $var wire 32 `# regfile(31) [31:0] $end
    $var wire 32 E# regfile(4) [31:0] $end
    $var wire 32 F# regfile(5) [31:0] $end
    $var wire 32 G# regfile(6) [31:0] $end
    $var wire 32 H# regfile(7) [31:0] $end
    $var wire 32 I# regfile(8) [31:0] $end
    $var wire 32 J# regfile(9) [31:0] $end
    $var wire  1 9' reset $end
    $var wire  1 )' reset_q $end
    $var wire 32 + rs1_value [31:0] $end
    $var wire 32 3 rs2_value [31:0] $end
    $var wire  1 k stage_1_en $end
    $var wire  1 !' stage_1_en_q $end
    $var wire  1 }) stage_1_ready $end
    $var wire  1 W" trap $end
    $var wire  1 W" trapped $end
    $var wire  1 w& trapped_q $end
   $upscope $end
  $upscope $end
 $upscope $end
$enddefinitions $end


#5
b00000000000000000000000000000000 #
b00000000000000000000000000000000 +
b00000000000000000000000000000000 3
b000000000000 ;
b0000000000000 C
b000000000000000000000 K
b00000000000000000000000000000000 S
b00000000000000000000000000000000 [
b00000000000000000000000000000000 c
0k
b00000000000000000000000000000000 s
b00000000000000000000000000000100 {
0%!
b00000000000000000000000000000000 -!
b0000 5!
b00000000000000000000000000000000 =!
1E!
0M!
0U!
b00000000000000000000000000000000 ]!
b00000000000000000000000000000000 e!
b0000 m!
0u!
b00000000000000000000000000000000 }!
b00000 '"
b00000 /"
b00000000000000000000000000000100 7"
0?"
b00000000000000000000000000000000 G"
1O"
0W"
b00000000000000000000000000000000 _"
b00000000000000000000000000000000 g"
b00000000000000000000000000000000 o"
0w"
b00000000000000000000000000000000 !#
0)#
b00000 1#
b00000 9#
b00000000000000000000000000000000 A#
b00000000000000000000000000000000 B#
b00000000000000000000000000000000 C#
b00000000000000000000000000000000 D#
b00000000000000000000000000000000 E#
b00000000000000000000000000000000 F#
b00000000000000000000000000000000 G#
b00000000000000000000000000000000 H#
b00000000000000000000000000000000 I#
b00000000000000000000000000000000 J#
b00000000000000000000000000000000 K#
b00000000000000000000000000000000 L#
b00000000000000000000000000000000 M#
b00000000000000000000000000000000 N#
b00000000000000000000000000000000 O#
b00000000000000000000000000000000 P#
b00000000000000000000000000000000 Q#
b00000000000000000000000000000000 R#
b00000000000000000000000000000000 S#
b00000000000000000000000000000000 T#
b00000000000000000000000000000000 U#
b00000000000000000000000000000000 V#
b00000000000000000000000000000000 W#
b00000000000000000000000000000000 X#
b00000000000000000000000000000000 Y#
b00000000000000000000000000000000 Z#
b00000000000000000000000000000000 [#
b00000000000000000000000000000000 \#
b00000000000000000000000000000000 ]#
b00000000000000000000000000000000 ^#
b00000000000000000000000000000000 _#
b00000000000000000000000000000000 `#
b00000000000000000000000000000000 '&
b00000000000000000000000000000000 /&
b0000000 7&
b00000 ?&
b00000 G&
b000 O&
b00000 W&
b0000000 _&
b000000000000 g&
b00000000000000000000000000000000 o&
0w&
0!'
0)'
01'
09'
b00000000000000000000000000010000 A'
b00000000000000000000000000000000 I'
b00000000000000000000000000100000 Q'
b0000011 Y'
b0100011 a'
b1000011 i'
b1100011 q'
b0000111 y'
b0100111 #(
b1000111 +(
b1100111 3(
b0001011 ;(
b0101011 C(
b1001011 K(
b1101011 S(
b0001111 [(
b0101111 c(
b1001111 k(
b1101111 s(
b0010011 {(
b0110011 %)
b1010011 -)
b1110011 5)
b0010111 =)
b0110111 E)
b1010111 M)
b1110111 U)
b0011011 ])
b0111011 e)
b1011011 m)
b1111011 u)
0})
#10
#15
b00000000000000000000000000000000 {
b00000000000000000000000000000000 7"
0O"
19'
#20
#25
b00000000000000000000000000000001 #
b000000001010 ;
b0000000001010 C
b00000000000000000000000000001010 S
b00000000000000000000000000001010 [
b00000000000000000000010100010011 _"
b11111111111111111111111111111100 '&
b01010 W&
b0010011 _&
1)'
11'
#30
#35
01'
#40
#45
b00000000000000000000000000000010 #
11'
#50
#55
01'
#60
#65
b00000000000000000000000000000011 #
11'
#70
#75
01'
#80
#85
b00000000000000000000000000000100 #
11'
#90
#95
01'
09'
#100
#105
b00000000000000000000000000000101 #
b00000000000000000000000000000100 {
b00000000000000000000000000000100 7"
1?"
b00000000000000000000000000000000 '&
0)'
11'
#110
#115
01'
#120
#125
b00000000000000000000000000000110 #
b001010000100000000000 K
b00000000000001010000100000000000 c
b00000000000000000000000000001000 {
b00000000000000000000000000001000 7"
b00000000000000000000000000000001 G"
b00000000000101010000010100010011 _"
b00000000000000000000000000000100 '&
b00000000000000000000000000000100 /&
b00001 ?&
b01010 G&
b000000000001 g&
b00000000000000000000000000000001 o&
11'
#130
#135
01'
#140
#145
b00000000000000000000000000000111 #
b00000000000000000000000000000001 +
b001010000000000000010 K
b00000000000001010000000000000010 c
b00000000000000000000000000001100 {
b00000000000000000000000000001100 7"
b00000000000000000000000000000011 G"
b00000000001001010000010100010011 _"
b00000000000000000000000000000001 K#
b00000000000000000000000000001000 '&
b00000000000000000000000000001000 /&
b00010 ?&
b000000000010 g&
b00000000000000000000000000000010 o&
11'
#150
#155
01'
#160
#165
b00000000000000000000000000001000 #
b00000000000000000000000000000011 +
b001010000100000000010 K
b00000000000001010000100000000010 c
b00000000000000000000000000010000 {
b00000000000000000000000000010000 7"
b00000000000000000000000000000110 G"
b00000000001101010000010100010011 _"
b00000000000000000000000000000011 K#
b00000000000000000000000000001100 '&
b00000000000000000000000000001100 /&
b00011 ?&
b000000000011 g&
b00000000000000000000000000000011 o&
11'
#170
#175
01'
#180
